oseti/__init__.py
oseti/oseti.py
oseti/dic/pn_noun.json
oseti/dic/pn_wago.json
oseti-0.4.3.1.dist-info/licenses/LICENSE
oseti-0.4.3.1.dist-info/METADATA
oseti-0.4.3.1.dist-info/WHEEL
oseti-0.4.3.1.dist-info/top_level.txt
oseti-0.4.3.1.dist-info/RECORD
