Metadata-Version: 2.4
Name: oseti
Version: 0.4.3.1
Summary: Dictionary based Sentiment Analysis for Japanese language
Author-email: Yukino Ikegami <yknikgm@gmail.com>
Maintainer-email: Yukino Ikegami <yknikgm@gmail.com>
Project-URL: Homepage, https://github.com/ikegami-yukino/oseti
Project-URL: Repository, https://github.com/ikegami-yukino/oseti.git
Project-URL: Issues, https://github.com/ikegami-yukino/oseti/issues
Project-URL: Changelog, https://github.com/ikegami-yukino/oseti/blob/master/CHANGELOG.md
Keywords: sentiment analysis,japanese,textpreprocessing,JapaneseText
Classifier: Development Status :: 4 - Beta
Classifier: Intended Audience :: Science/Research
Classifier: Intended Audience :: Information Technology
Classifier: Intended Audience :: Developers
Classifier: Natural Language :: Japanese
Classifier: License :: OSI Approved :: MIT License
Classifier: Programming Language :: Python
Classifier: Programming Language :: Python :: 3
Classifier: Programming Language :: Python :: 3.9
Classifier: Programming Language :: Python :: 3.10
Classifier: Programming Language :: Python :: 3.11
Classifier: Programming Language :: Python :: 3.12
Classifier: Programming Language :: Python :: 3.13
Classifier: Topic :: Text Processing
Classifier: Topic :: Text Processing :: Linguistic
License-File: LICENSE
Requires-Dist: bunkai
Requires-Dist: mecab
Provides-Extra: test
Requires-Dist: pytest; extra == "test"
Dynamic: license-file
Dynamic: requires-dist
